setup.py
avos/__init__.py
avos/avos.py
avos/version.py
avos.egg-info/PKG-INFO
avos.egg-info/SOURCES.txt
avos.egg-info/dependency_links.txt
avos.egg-info/entry_points.txt
avos.egg-info/requires.txt
avos.egg-info/top_level.txt
tests/__init__.py
tests/base.py
tests/test.py
tests/test_version.py