Metadata-Version: 1.1
Name: avos
Version: 0.1.0
Summary: an incredible python package
Home-page: https://github.com/wumaogit/avos
Author: wumaogit
Author-email: actor2019@gmail.com
License: MIT
Keywords: avos avoscloud
Platform: UNKNOWN
Classifier: Development Status :: 4 - Beta
Classifier: Intended Audience :: Developers
Classifier: License :: OSI Approved :: MIT License
Classifier: Natural Language :: English
Classifier: Operating System :: Unix
Classifier: Programming Language :: Python :: 2.7
Classifier: Programming Language :: Python :: 3.4
Classifier: Programming Language :: Python :: Implementation :: PyPy
Classifier: Operating System :: OS Independent
